neemuds/LICENSE.md
neemuds/__init__.py
neemuds/local_params.py
neemuds/mcmc_config_parser.py
neemuds/mcmc_deprecated_conf_parser.py
neemuds/params.py
neemuds/planet_params.py
neemuds/updf.py
neemuds/data/conf/neemuds_earth.conf
neemuds/data/conf/neemuds_earth.ini
neemuds/data/conf/neemuds_local.conf
neemuds/data/conf/neemuds_local.ini
neemuds/data/conf/neemuds_mars.conf
neemuds/data/conf/neemuds_mars.ini
neemuds/data/conf/neemuds_mcmc.ini
neemuds/data/conf/neemuds_mcmc_earth.conf
neemuds/data/conf/neemuds_mcmc_mars.conf
neemuds/data/prior/mod_earth_rayl_hi
neemuds/data/prior/mod_earth_rayl_lo
neemuds/data/prior/mod_loc_hi
neemuds/data/prior/mod_loc_lo
neemuds/data/prior/prem_noocean.txt
neemuds/data/prior/prem_ocean.txt
neemuds/data/prior/mars/DWThot.tvel
neemuds/data/prior/mars/DWThotCrust1.tvel
neemuds/data/prior/mars/DWThotCrust1r.tvel
neemuds/data/prior/mars/EH45Tcold.tvel
neemuds/data/prior/mars/EH45TcoldCrust1.tvel
neemuds/data/prior/mars/EH45TcoldCrust1r.tvel
neemuds/data/prior/mars/EH45ThotCrust2.tvel
neemuds/data/prior/mars/EH45ThotCrust2r.tvel
neemuds/data/sismos/2006319BFOBHZ.sac
neemuds/data/sismos/#03_1999.228.23.02/1999.228.23.02.20.0369.II.KDAK.00.BHE.M.SAC
neemuds/data/sismos/#03_1999.228.23.02/1999.228.23.02.20.0370.II.KDAK.00.BHN.M.SAC
neemuds/data/sismos/#03_1999.228.23.02/1999.228.23.02.20.0370.II.KDAK.00.BHZ.M.SAC
neemuds/data/sismos/#03_1999.228.23.02/RESP.II.KDAK.00.BHE
neemuds/data/sismos/#03_1999.228.23.02/RESP.II.KDAK.00.BHN
neemuds/data/sismos/#03_1999.228.23.02/RESP.II.KDAK.00.BHZ
neemuds/data/sismos/cc/cc_sum_E137_PY48.sacn
neemuds-2.16.21.data/scripts/neem_calc_post_pdf_model_score.py
neemuds-2.16.21.data/scripts/neem_check_mcmc_conf.py
neemuds-2.16.21.data/scripts/neem_gen_mcmc_config.py
neemuds-2.16.21.data/scripts/neem_prior_builder.py
neemuds-2.16.21.data/scripts/neemuds_herrmann.py
neemuds-2.16.21.data/scripts/neemuds_mcmc.py
neemuds-2.16.21.data/scripts/neemuds_mineos.py
neemuds-2.16.21.data/scripts/neemuds_plot_Xpost_pdf.py
neemuds-2.16.21.dist-info/licenses/LICENSE.md
neemuds-2.16.21.dist-info/METADATA
neemuds-2.16.21.dist-info/WHEEL
neemuds-2.16.21.dist-info/top_level.txt
neemuds-2.16.21.dist-info/RECORD
